sheepped/__init__.py
sheepped/usps.py
sheepped-0.0.1.dist-info/LICENSE
sheepped-0.0.1.dist-info/METADATA
sheepped-0.0.1.dist-info/WHEEL
sheepped-0.0.1.dist-info/top_level.txt
sheepped-0.0.1.dist-info/RECORD
