Metadata-Version: 2.1
Name: sheepped
Version: 0.0.1
Summary: A Python wrapper for tracking delivery!
Home-page: https://github.com/g4brielvs/sheepped
Author: Gabriel Stefanini
Author-email: g4brielvs@gbrielvs.me
License: UNKNOWN
Keywords: shipping
Platform: UNKNOWN
Classifier: Programming Language :: Python :: 3
Classifier: License :: OSI Approved :: MIT License
Classifier: Operating System :: OS Independent
Classifier: Development Status :: 3 - Alpha
Classifier: Topic :: Software Development :: Libraries :: Python Modules
Classifier: Topic :: Software Development :: Testing
Classifier: Topic :: Utilities
Requires-Dist: requests
Requires-Dist: lxml
Requires-Dist: xmltodict
